realjam/__init__.py
realjam/agent_interface.py
realjam/cli.py
realjam/onnx_kv.py
realjam/onnx_wrapper.py
realjam/prepare_onnx.py
realjam/server.py
realjam/core/__init__.py
realjam/core/constants.py
realjam/core/data_utils.py
realjam/core/gen_model.py
realjam/core/inference_utils.py
realjam/core/sampling.py
realjam/core/tokenizer.py
realjam/core/transformers.py
realjam/frontend/index.html
realjam/frontend/main.js
realjam/frontend/note_visualization.js
realjam/frontend/play_from_midi_input.js
realjam/frontend/style.css
realjam/frontend/tonejs_instruments.js
realjam/utils/__init__.py
realjam/utils/downloader.py
realjam-1.0.0.dist-info/licenses/LICENSE
realjam-1.0.0.dist-info/METADATA
realjam-1.0.0.dist-info/WHEEL
realjam-1.0.0.dist-info/entry_points.txt
realjam-1.0.0.dist-info/top_level.txt
realjam-1.0.0.dist-info/RECORD
